gamechanger_client/__init__.py
gamechanger_client/config.py
gamechanger_client/exceptions.py
gamechanger_client/http_session.py
gamechanger_client/version.py
gamechanger_client/endpoints/clips.py
gamechanger_client/endpoints/game_streams.py
gamechanger_client/endpoints/me.py
gamechanger_client/endpoints/organizations.py
gamechanger_client/endpoints/players.py
gamechanger_client/endpoints/public.py
gamechanger_client/endpoints/rest_endpoint.py
gamechanger_client/endpoints/search.py
gamechanger_client/endpoints/teams.py
gamechanger_client-0.0.6.dist-info/METADATA
gamechanger_client-0.0.6.dist-info/WHEEL
gamechanger_client-0.0.6.dist-info/licenses/LICENSE
gamechanger_client-0.0.6.dist-info/RECORD
