Metadata-Version: 2.4
Name: gamechanger_client
Version: 0.0.6
Summary: An easy-to-use wrapper for interacting with the GameChanger APIs
Project-URL: Homepage, https://github.com/TheAlanNix/gamechanger-client
Project-URL: Issues, https://github.com/TheAlanNix/gamechanger-client/issues
Author-email: Alan Nix <alan@alannix.com>
License-Expression: MIT
License-File: LICENSE
Classifier: Operating System :: OS Independent
Classifier: Programming Language :: Python :: 3
Requires-Python: >=3.9
